wasp/__init__.py
wasp/gem/__init__.py
wasp/gem/gap_filling.py
wasp/gem/run_gem.py
wasp/gem/rxn2uniprot.py
wasp/main/SAFE_enrichment.py
wasp/main/__init__.py
wasp/main/fs_besthits.py
wasp/main/generate_network.py
wasp/main/parse_fs.py
wasp/main/retrieve_annotation.py
wasp/main/run.py
wasp/main/safepy/__init__.py
wasp/main/safepy/safe.py
wasp/main/safepy/safe_default.ini
wasp/main/safepy/safe_extras.py
wasp/main/safepy/safe_io.py
wasp/utils/__init__.py
wasp/utils/fasta2pdb/__init__.py
wasp/utils/fasta2pdb/afdb_downloader.py
wasp/utils/fasta2pdb/predict_structures.py
wasp/utils/gem_preprocessing/__init__.py
wasp/utils/gem_preprocessing/find_orphans.py
wasp/utils/gem_preprocessing/reac_xref.tsv
wasp/utils/gem_preprocessing/rxn2code.py
wasp_proteins_annotation-1.0.1.dist-info/licenses/LICENSE
wasp_proteins_annotation-1.0.1.dist-info/METADATA
wasp_proteins_annotation-1.0.1.dist-info/WHEEL
wasp_proteins_annotation-1.0.1.dist-info/entry_points.txt
wasp_proteins_annotation-1.0.1.dist-info/top_level.txt
wasp_proteins_annotation-1.0.1.dist-info/RECORD
