Metadata-Version: 2.4
Name: wasp-proteins-annotation
Version: 1.0.1
Summary: WASP: A computational pipeline for protein functional annotation using structural information.
Home-page: https://github.com/gioodm/WASP
Author: Giorgia Del Missier
Author-email: Giorgia Del Missier <delmissiergiorgia@gmail.com>
License: MIT License
Project-URL: Homepage, https://github.com/gioodm/WASP
Requires-Python: >=3.9
License-File: LICENSE
Requires-Dist: altair==5.2.0
Requires-Dist: altair-data-server==0.4.1
Requires-Dist: altair-saver==0.5.0
Requires-Dist: altair-viewer==0.4.0
Requires-Dist: biopython==1.84
Requires-Dist: cobra==0.29.0
Requires-Dist: matplotlib==3.9.0
Requires-Dist: multiprocess==0.70.16
Requires-Dist: networkx==3.3
Requires-Dist: numpy==1.26.4
Requires-Dist: openpyxl==3.1.2
Requires-Dist: pandas==2.2.2
Requires-Dist: requests==2.32.2
Requires-Dist: scipy==1.11.4
Requires-Dist: statsmodels==0.14.2
Requires-Dist: tqdm==4.66.4
Requires-Dist: urllib3==2.2.1
Requires-Dist: vl-convert-python==1.4.0
Requires-Dist: XlsxWriter==3.2.0
Dynamic: author
Dynamic: home-page
Dynamic: license-file
Dynamic: requires-python
